promptly/__init__.py
promptly/image_fetcher.py
promptly/main.py
promptly_whatsapp-0.1.0.dist-info/METADATA
promptly_whatsapp-0.1.0.dist-info/WHEEL
promptly_whatsapp-0.1.0.dist-info/top_level.txt
promptly_whatsapp-0.1.0.dist-info/RECORD
