Metadata-Version: 2.4
Name: promptly-whatsapp
Version: 0.1.0
Summary: Send custom prompted messages with beautiful images via WhatsApp automatically
Home-page: https://github.com/itsmeved24/Promptly
Author: Vedank
Author-email: your.email@example.com
Classifier: Programming Language :: Python :: 3
Classifier: License :: OSI Approved :: MIT License
Classifier: Operating System :: OS Independent
Requires-Python: >=3.6
Requires-Dist: schedule
Requires-Dist: pywhatkit
Requires-Dist: requests
Requires-Dist: pyautogui
Requires-Dist: python-dotenv
Dynamic: author
Dynamic: author-email
Dynamic: classifier
Dynamic: description
Dynamic: description-content-type
Dynamic: home-page
Dynamic: requires-dist
Dynamic: requires-python
Dynamic: summary
